{"text": " podcastfrancaisfacile.com Qu'est-ce que vous faites le week-end en g\u00e9n\u00e9ral ? Le week-end, le samedi, j'ai ma le\u00e7on de guitare. Apr\u00e8s, je vais souvent au cin\u00e9ma avec des amis. Vous jouez de la guitare classique ? Non, je fais de la guitare folk. Et le dimanche, que faites-vous ? Le dimanche, je fais la grasse matin\u00e9e. Et puis, je fais le m\u00e9nage. Mais s'il fait beau, je pr\u00e9f\u00e8re aller \u00e0 la montagne ou \u00e0 la mer. Et vous, qu'est-ce que vous faites le week-end en g\u00e9n\u00e9ral ? Moi, je travaille le samedi. Mais le samedi soir, je sors souvent avec mes coll\u00e8gues apr\u00e8s le travail. Et le dimanche, vous ne travaillez pas ? Non, heureusement. Alors le dimanche matin, moi aussi, je fais la grasse matin\u00e9e. Et l'apr\u00e8s-midi, je vois des amis ou je fais du shopping.", "segments": [{"id": 0, "seek": 0, "start": 0.0, "end": 4.0, "text": " podcastfrancaisfacile.com", "tokens": [50364, 7367, 69, 4257, 496, 4937, 326, 794, 13, 1112, 50564], "temperature": 0.0, "avg_logprob": -0.193944779953154, "compression_ratio": 1.4221105527638191, "no_speech_prob": 0.09383833408355713}, {"id": 1, "seek": 0, "start": 4.0, "end": 8.0, "text": " Qu'est-ce que vous faites le week-end en g\u00e9n\u00e9ral ?", "tokens": [50564, 2326, 6, 377, 12, 384, 631, 2630, 29902, 476, 1243, 12, 521, 465, 27796, 2506, 50764], "temperature": 0.0, "avg_logprob": -0.193944779953154, "compression_ratio": 1.4221105527638191, "no_speech_prob": 0.09383833408355713}, {"id": 2, "seek": 0, "start": 8.0, "end": 14.0, "text": " Le week-end, le samedi, j'ai ma le\u00e7on de guitare.", "tokens": [50764, 1456, 1243, 12, 521, 11, 476, 3247, 10323, 11, 361, 6, 1301, 463, 476, 17134, 368, 31108, 543, 13, 51064], "temperature": 0.0, "avg_logprob": -0.193944779953154, "compression_ratio": 1.4221105527638191, "no_speech_prob": 0.09383833408355713}, {"id": 3, "seek": 0, "start": 14.0, "end": 19.0, "text": " Apr\u00e8s, je vais souvent au cin\u00e9ma avec des amis.", "tokens": [51064, 29265, 11, 1506, 9369, 20847, 1609, 6539, 50201, 4163, 730, 32929, 13, 51314], "temperature": 0.0, "avg_logprob": -0.193944779953154, "compression_ratio": 1.4221105527638191, "no_speech_prob": 0.09383833408355713}, {"id": 4, "seek": 0, "start": 19.0, "end": 22.0, "text": " Vous jouez de la guitare classique ?", "tokens": [51314, 10802, 11110, 4371, 368, 635, 31108, 543, 1508, 1925, 2506, 51464], "temperature": 0.0, "avg_logprob": -0.193944779953154, "compression_ratio": 1.4221105527638191, "no_speech_prob": 0.09383833408355713}, {"id": 5, "seek": 0, "start": 22.0, "end": 25.0, "text": " Non, je fais de la guitare folk.", "tokens": [51464, 8774, 11, 1506, 12153, 368, 635, 31108, 543, 15748, 13, 51614], "temperature": 0.0, "avg_logprob": -0.193944779953154, "compression_ratio": 1.4221105527638191, "no_speech_prob": 0.09383833408355713}, {"id": 6, "seek": 0, "start": 25.0, "end": 28.0, "text": " Et le dimanche, que faites-vous ?", "tokens": [51614, 3790, 476, 5013, 22806, 11, 631, 29902, 12, 16514, 2506, 51764], "temperature": 0.0, "avg_logprob": -0.193944779953154, "compression_ratio": 1.4221105527638191, "no_speech_prob": 0.09383833408355713}, {"id": 7, "seek": 2800, "start": 28.0, "end": 32.0, "text": " Le dimanche, je fais la grasse matin\u00e9e.", "tokens": [50364, 1456, 5013, 22806, 11, 1506, 12153, 635, 677, 8604, 33389, 3856, 13, 50564], "temperature": 0.0, "avg_logprob": -0.140248181527121, "compression_ratio": 1.624413145539906, "no_speech_prob": 0.03159458935260773}, {"id": 8, "seek": 2800, "start": 32.0, "end": 35.0, "text": " Et puis, je fais le m\u00e9nage.", "tokens": [50564, 3790, 9093, 11, 1506, 12153, 476, 275, 3516, 609, 13, 50714], "temperature": 0.0, "avg_logprob": -0.140248181527121, "compression_ratio": 1.624413145539906, "no_speech_prob": 0.03159458935260773}, {"id": 9, "seek": 2800, "start": 35.0, "end": 40.0, "text": " Mais s'il fait beau, je pr\u00e9f\u00e8re aller \u00e0 la montagne ou \u00e0 la mer.", "tokens": [50714, 6313, 262, 6, 388, 3887, 29891, 11, 1506, 31139, 4212, 8722, 1531, 635, 8143, 13887, 2820, 1531, 635, 3551, 13, 50964], "temperature": 0.0, "avg_logprob": -0.140248181527121, "compression_ratio": 1.624413145539906, "no_speech_prob": 0.03159458935260773}, {"id": 10, "seek": 2800, "start": 40.0, "end": 45.0, "text": " Et vous, qu'est-ce que vous faites le week-end en g\u00e9n\u00e9ral ?", "tokens": [50964, 3790, 2630, 11, 421, 6, 377, 12, 384, 631, 2630, 29902, 476, 1243, 12, 521, 465, 27796, 2506, 51214], "temperature": 0.0, "avg_logprob": -0.140248181527121, "compression_ratio": 1.624413145539906, "no_speech_prob": 0.03159458935260773}, {"id": 11, "seek": 2800, "start": 45.0, "end": 47.0, "text": " Moi, je travaille le samedi.", "tokens": [51214, 20256, 11, 1506, 41072, 476, 3247, 10323, 13, 51314], "temperature": 0.0, "avg_logprob": -0.140248181527121, "compression_ratio": 1.624413145539906, "no_speech_prob": 0.03159458935260773}, {"id": 12, "seek": 2800, "start": 47.0, "end": 53.0, "text": " Mais le samedi soir, je sors souvent avec mes coll\u00e8gues apr\u00e8s le travail.", "tokens": [51314, 6313, 476, 3247, 10323, 27105, 11, 1506, 262, 830, 20847, 4163, 3813, 1263, 30370, 1247, 13274, 476, 18047, 13, 51614], "temperature": 0.0, "avg_logprob": -0.140248181527121, "compression_ratio": 1.624413145539906, "no_speech_prob": 0.03159458935260773}, {"id": 13, "seek": 2800, "start": 53.0, "end": 57.0, "text": " Et le dimanche, vous ne travaillez pas ?", "tokens": [51614, 3790, 476, 5013, 22806, 11, 2630, 408, 41072, 89, 1736, 2506, 51814], "temperature": 0.0, "avg_logprob": -0.140248181527121, "compression_ratio": 1.624413145539906, "no_speech_prob": 0.03159458935260773}, {"id": 14, "seek": 5700, "start": 57.0, "end": 59.0, "text": " Non, heureusement.", "tokens": [50364, 8774, 11, 30027, 21359, 13, 50464], "temperature": 0.0, "avg_logprob": -0.15806380738603307, "compression_ratio": 1.2155172413793103, "no_speech_prob": 0.0032720165327191353}, {"id": 15, "seek": 5700, "start": 59.0, "end": 64.0, "text": " Alors le dimanche matin, moi aussi, je fais la grasse matin\u00e9e.", "tokens": [50464, 9946, 476, 5013, 22806, 33389, 11, 7748, 6212, 11, 1506, 12153, 635, 677, 8604, 33389, 3856, 13, 50714], "temperature": 0.0, "avg_logprob": -0.15806380738603307, "compression_ratio": 1.2155172413793103, "no_speech_prob": 0.0032720165327191353}, {"id": 16, "seek": 5700, "start": 64.0, "end": 69.0, "text": " Et l'apr\u00e8s-midi, je vois des amis ou je fais du shopping.", "tokens": [50714, 3790, 287, 6, 48240, 12, 76, 12716, 11, 1506, 18297, 730, 32929, 2820, 1506, 12153, 1581, 8688, 13, 50964], "temperature": 0.0, "avg_logprob": -0.15806380738603307, "compression_ratio": 1.2155172413793103, "no_speech_prob": 0.0032720165327191353}], "language": "fr"}